unionbio/__init__.py
unionbio/apps/alignment_dashboard.py
unionbio/config.py
unionbio/tasks/__init__.py
unionbio/tasks/base_recal.py
unionbio/tasks/bowtie2.py
unionbio/tasks/bwa.py
unionbio/tasks/fastp.py
unionbio/tasks/fastqc.py
unionbio/tasks/folding.py
unionbio/tasks/haplotype_caller.py
unionbio/tasks/helpers.py
unionbio/tasks/hisat2.py
unionbio/tasks/mark_dups.py
unionbio/tasks/multiqc.py
unionbio/tasks/parabricks.py
unionbio/tasks/sort_sam.py
unionbio/tasks/utils.py
unionbio/types/__init__.py
unionbio/types/alignment.py
unionbio/types/protein.py
unionbio/types/reads.py
unionbio/types/reference.py
unionbio/types/variants.py
unionbio/workflows/__init__.py
unionbio/workflows/alignment.py
unionbio/workflows/compare_aligners.py
unionbio/workflows/parabricks_wgs_calling.py
unionbio/workflows/simple_alignment.py
unionbio/workflows/simple_variant_calling.py
unionbio-0.1.1.dist-info/LICENSE
unionbio-0.1.1.dist-info/METADATA
unionbio-0.1.1.dist-info/WHEEL
unionbio-0.1.1.dist-info/entry_points.txt
unionbio-0.1.1.dist-info/RECORD
