Metadata-Version: 2.1
Name: unionbio
Version: 0.1.1
Summary: 
Author: pryce-turner
Author-email: pryce.turner@gmail.com
Requires-Python: >=3.10,<3.13
Classifier: Programming Language :: Python :: 3
Classifier: Programming Language :: Python :: 3.10
Classifier: Programming Language :: Python :: 3.11
Classifier: Programming Language :: Python :: 3.12
Requires-Dist: docker (<7.0.0)
Requires-Dist: flytekit (>=1.12.0,<2.0.0)
Requires-Dist: flytekitplugins-envd (>=1.12.3,<2.0.0)
Requires-Dist: imagespec-fast-builder (==0.0.33)
Requires-Dist: requests (==2.31.0)
Requires-Dist: streamlit (>=1.36.0,<2.0.0)
Requires-Dist: union[byoc] (>=0.1.66,<0.2.0)
